TestPipScript_Malasaur/Test.py
TestPipScript_Malasaur/__init__.py
TestPipScript_Malasaur-0.0.1.dist-info/LICENCE
TestPipScript_Malasaur-0.0.1.dist-info/METADATA
TestPipScript_Malasaur-0.0.1.dist-info/WHEEL
TestPipScript_Malasaur-0.0.1.dist-info/top_level.txt
TestPipScript_Malasaur-0.0.1.dist-info/RECORD
