Metadata-Version: 2.1
Name: TestPipScript-Malasaur
Version: 0.0.1
Summary: A test package. Will be used for a pip automation script. This package has no use.
Author-email: Malasaur <amuntenci.silvio@gmail.com>
Project-URL: Homepage, https://github.com/pypa/sampleproject
Project-URL: Bug Tracker, https://github.com/pypa/sampleproject/issues
Classifier: Programming Language :: Python :: 3
Classifier: License :: OSI Approved :: MIT License
Classifier: Operating System :: OS Independent
Requires-Python: >=3.7
License-File: LICENCE
